org_du-2018.02.03.01.dist-info/DESCRIPTION.rst
org_du-2018.02.03.01.dist-info/METADATA
org_du-2018.02.03.01.dist-info/RECORD
org_du-2018.02.03.01.dist-info/WHEEL
org_du-2018.02.03.01.dist-info/entry_points.txt
org_du-2018.02.03.01.dist-info/metadata.json
org_du-2018.02.03.01.dist-info/top_level.txt
orgdu/__init__.py
