Metadata-Version: 2.0
Name: org-du
Version: 2018.02.03.01
Summary: du-like output for lines of GNU/Emacs Org-mode files
Home-page: https://github.com/novoid/du-org
Author: Karl Voit
Author-email: tools@Karl-Voit.at
License: UNKNOWN
Download-URL: https://github.com/novoid/du-org/zipball/master
Keywords: orgmode,org-mode,du,xdu,visualization
Platform: UNKNOWN
Classifier: Programming Language :: Python :: 3 :: Only
Classifier: Development Status :: 5 - Production/Stable
Classifier: Environment :: Console
Classifier: Intended Audience :: End Users/Desktop
Classifier: License :: OSI Approved :: GNU General Public License (GPL)
Classifier: Operating System :: OS Independent
